octopus_energy_client/__init__.py
octopus_energy_client/client.py
octopus_energy_client/enums.py
octopus_energy_client/util.py
octopus_energy_client-0.0.12.dist-info/LICENSE
octopus_energy_client-0.0.12.dist-info/METADATA
octopus_energy_client-0.0.12.dist-info/WHEEL
octopus_energy_client-0.0.12.dist-info/top_level.txt
octopus_energy_client-0.0.12.dist-info/RECORD
