Metadata-Version: 2.1
Name: octopus-energy-client
Version: 0.0.12
Summary: A Python API for retrieving Octopus Energy data
Home-page: https://github.com/ChristopherJohnston/octopus_energy
Author: Christopher P Johnston
Author-email: c.p.johnston@gmail.com
License: MIT
Project-URL: Bug Tracker, https://github.com/ChristopherJohnston/octopus_energy/issues
Platform: UNKNOWN
Classifier: License :: OSI Approved :: MIT License
Classifier: Programming Language :: Python :: 3
Classifier: Programming Language :: Python :: 3.8
Requires-Python: >=3.6
License-File: LICENSE
Requires-Dist: requests
Requires-Dist: pytz
